PylesLib/__init__.py
PylesLib/pyleslib.py
PylesLib-0.0.2.dist-info/LICENSE
PylesLib-0.0.2.dist-info/METADATA
PylesLib-0.0.2.dist-info/WHEEL
PylesLib-0.0.2.dist-info/top_level.txt
PylesLib-0.0.2.dist-info/RECORD
